{
 "charts": [],
 "content": "[{\"type\":\"header\",\"data\":{\"text\":\"<span class=\\\"h4\\\"><b>Seus atalhos</b></span>\",\"col\":12}},{\"type\":\"shortcut\",\"data\":{\"shortcut_name\":\"Oportunidade\",\"col\":3}},{\"type\":\"shortcut\",\"data\":{\"shortcut_name\":\"Customer\",\"col\":3}},{\"type\":\"shortcut\",\"data\":{\"shortcut_name\":\"Or\u00e7amento\",\"col\":3}},{\"type\":\"shortcut\",\"data\":{\"shortcut_name\":\"Pedido de Venda\",\"col\":3}},{\"type\":\"shortcut\",\"data\":{\"shortcut_name\":\"Fatura de Venda\",\"col\":3}},{\"type\":\"shortcut\",\"data\":{\"shortcut_name\":\"Item\",\"col\":3}},{\"type\":\"shortcut\",\"data\":{\"shortcut_name\":\"Dashboard\",\"col\":3}},{\"type\":\"shortcut\",\"data\":{\"shortcut_name\":\"Fornecedor\",\"col\":3}},{\"type\":\"shortcut\",\"data\":{\"shortcut_name\":\"Fatura de Compra\",\"col\":3}},{\"type\":\"spacer\",\"data\":{\"col\":12}},{\"type\":\"header\",\"data\":{\"text\":\"<span class=\\\"h4\\\"><b>Ordem de Servi\u00e7o</b></span>\",\"col\":12}},{\"type\":\"shortcut\",\"data\":{\"shortcut_name\":\"Ordem de Servi\u00e7o Interna\",\"col\":5}},{\"type\":\"shortcut\",\"data\":{\"shortcut_name\":\"Ordem de Servi\u00e7o Externa\",\"col\":5}},{\"type\":\"shortcut\",\"data\":{\"shortcut_name\":\"Equipamentos do Cliente\",\"col\":5}}]",
 "creation": "2020-01-23 13:46:38.833076",
 "docstatus": 0,
 "doctype": "Workspace",
 "for_user": "",
 "hide_custom": 0,
 "icon": "getting-started",
 "idx": 0,
 "is_hidden": 0,
 "label": "Home",
 "links": [
  {
   "dependencies": "",
   "hidden": 0,
   "is_query_report": 0,
   "label": "Chart of Accounts",
   "link_count": 0,
   "link_to": "Account",
   "link_type": "DocType",
   "onboard": 1,
   "type": "Link"
  },
  {
   "dependencies": "",
   "hidden": 0,
   "is_query_report": 0,
   "label": "Company",
   "link_count": 0,
   "link_to": "Company",
   "link_type": "DocType",
   "onboard": 1,
   "type": "Link"
  },
  {
   "dependencies": "",
   "hidden": 0,
   "is_query_report": 0,
   "label": "Customer",
   "link_count": 0,
   "link_to": "Customer",
   "link_type": "DocType",
   "onboard": 1,
   "type": "Link"
  },
  {
   "dependencies": "",
   "hidden": 0,
   "is_query_report": 0,
   "label": "Supplier",
   "link_count": 0,
   "link_to": "Supplier",
   "link_type": "DocType",
   "onboard": 1,
   "type": "Link"
  },
  {
   "dependencies": "",
   "hidden": 0,
   "is_query_report": 0,
   "label": "Item",
   "link_count": 0,
   "link_to": "Item",
   "link_type": "DocType",
   "onboard": 1,
   "type": "Link"
  },
  {
   "dependencies": "",
   "hidden": 0,
   "is_query_report": 0,
   "label": "Warehouse",
   "link_count": 0,
   "link_to": "Warehouse",
   "link_type": "DocType",
   "onboard": 1,
   "type": "Link"
  },
  {
   "dependencies": "",
   "hidden": 0,
   "is_query_report": 0,
   "label": "Brand",
   "link_count": 0,
   "link_to": "Brand",
   "link_type": "DocType",
   "onboard": 1,
   "type": "Link"
  },
  {
   "dependencies": "",
   "hidden": 0,
   "is_query_report": 0,
   "label": "Unit of Measure (UOM)",
   "link_count": 0,
   "link_to": "UOM",
   "link_type": "DocType",
   "onboard": 1,
   "type": "Link"
  },
  {
   "dependencies": "",
   "hidden": 0,
   "is_query_report": 0,
   "label": "Stock Reconciliation",
   "link_count": 0,
   "link_to": "Stock Reconciliation",
   "link_type": "DocType",
   "onboard": 1,
   "type": "Link"
  },
  {
   "dependencies": "",
   "hidden": 0,
   "is_query_report": 0,
   "label": "Lead",
   "link_count": 0,
   "link_to": "Lead",
   "link_type": "DocType",
   "onboard": 1,
   "type": "Link"
  },
  {
   "dependencies": "",
   "hidden": 0,
   "is_query_report": 0,
   "label": "Customer Group",
   "link_count": 0,
   "link_to": "Customer Group",
   "link_type": "DocType",
   "onboard": 1,
   "type": "Link"
  },
  {
   "dependencies": "",
   "hidden": 0,
   "is_query_report": 0,
   "label": "Territory",
   "link_count": 0,
   "link_to": "Territory",
   "link_type": "DocType",
   "onboard": 1,
   "type": "Link"
  },
  {
   "dependencies": "",
   "hidden": 0,
   "is_query_report": 0,
   "label": "Import Data",
   "link_count": 0,
   "link_to": "Data Import",
   "link_type": "DocType",
   "onboard": 1,
   "type": "Link"
  },
  {
   "dependencies": "",
   "hidden": 0,
   "is_query_report": 0,
   "label": "Opening Invoice Creation Tool",
   "link_count": 0,
   "link_to": "Opening Invoice Creation Tool",
   "link_type": "DocType",
   "onboard": 1,
   "type": "Link"
  },
  {
   "dependencies": "",
   "hidden": 0,
   "is_query_report": 0,
   "label": "Chart of Accounts Importer",
   "link_count": 0,
   "link_to": "Chart of Accounts Importer",
   "link_type": "DocType",
   "onboard": 1,
   "type": "Link"
  },
  {
   "dependencies": "",
   "hidden": 0,
   "is_query_report": 0,
   "label": "Letter Head",
   "link_count": 0,
   "link_to": "Letter Head",
   "link_type": "DocType",
   "onboard": 1,
   "type": "Link"
  },
  {
   "dependencies": "",
   "hidden": 0,
   "is_query_report": 0,
   "label": "Email Account",
   "link_count": 0,
   "link_to": "Email Account",
   "link_type": "DocType",
   "onboard": 1,
   "type": "Link"
  }
 ],
 "modified": "2024-04-18 10:54:17.510128",
 "modified_by": "Administrator",
 "module": "Ordem Servico",
 "name": "Home",
 "owner": "Administrator",
 "parent_page": "",
 "public": 1,
 "quick_lists": [],
 "restrict_to_domain": "",
 "roles": [],
 "sequence_id": 1.0,
 "shortcuts": [
  {
   "color": "Blue",
   "doc_view": "List",
   "label": "Ordem de Servi\u00e7o Interna",
   "link_to": "Ordem Servico Interna",
   "type": "DocType"
  },
  {
   "color": "Grey",
   "doc_view": "List",
   "label": "Fornecedor",
   "link_to": "Supplier",
   "type": "DocType"
  },
  {
   "color": "Green",
   "label": "Fatura de Venda",
   "link_to": "Sales Invoice",
   "type": "DocType"
  },
  {
   "color": "Grey",
   "doc_view": "List",
   "label": "Fatura de Compra",
   "link_to": "Purchase Invoice",
   "type": "DocType"
  },
  {
   "color": "Blue",
   "doc_view": "List",
   "label": "Oportunidade",
   "link_to": "Opportunity",
   "type": "DocType"
  },
  {
   "color": "Red",
   "doc_view": "List",
   "label": "Or\u00e7amento",
   "link_to": "Quotation",
   "type": "DocType"
  },
  {
   "label": "Item",
   "link_to": "Item",
   "type": "DocType"
  },
  {
   "color": "Blue",
   "doc_view": "List",
   "label": "Ordem de Servi\u00e7o Externa",
   "link_to": "Ordem Servico Externa",
   "type": "DocType"
  },
  {
   "color": "Blue",
   "doc_view": "List",
   "label": "Equipamentos do Cliente",
   "link_to": "Equipamentos do Cliente",
   "type": "DocType"
  },
  {
   "color": "Green",
   "doc_view": "List",
   "label": "Pedido de Venda",
   "link_to": "Sales Order",
   "type": "DocType"
  },
  {
   "color": "Grey",
   "doc_view": "List",
   "label": "Dashboard",
   "link_to": "dashboard-view",
   "type": "Page"
  },
  {
   "label": "Customer",
   "link_to": "Customer",
   "type": "DocType"
  }
 ],
 "title": "Home"
}
